pacli/__init__.py
pacli/cli.py
pacli/decorators.py
pacli/helpers.py
pacli/linklyhq.py
pacli/log.py
pacli/ssh_utils.py
pacli/store.py
pacli/commands/__init__.py
pacli/commands/admin.py
pacli/commands/ai.py
pacli/commands/secrets.py
pacli/commands/ssh.py
pacli/commands/utils.py
pacli/commands/web.py
pacli/web/__init__.py
pacli/web/app.py
pacli/web/ssh_handler.py
pacli/web/static/app.js
pacli/web/static/style.css
pacli/web/templates/index.html
pacli_tool-1.3.1.dist-info/licenses/LICENSE
pacli_tool-1.3.1.dist-info/METADATA
pacli_tool-1.3.1.dist-info/WHEEL
pacli_tool-1.3.1.dist-info/entry_points.txt
pacli_tool-1.3.1.dist-info/top_level.txt
pacli_tool-1.3.1.dist-info/RECORD
