Metadata-Version: 2.4
Name: pacli-tool
Version: 1.3.1
Summary: A secure CLI to manage secrets locally with encryption, master password, and clipboard support.
Author-email: Mobarak Hosen Shakil <mh.ice.iu@gmail.com>
License: MIT License
Project-URL: Homepage, https://github.com/imshakil/pacli
Project-URL: Issues, https://github.com/imshakil/pacli/issues
Keywords: cli,secrets,encryption,password,token,clipboard,security
Classifier: Programming Language :: Python :: 3
Classifier: License :: OSI Approved :: MIT License
Classifier: Operating System :: OS Independent
Classifier: Environment :: Console
Classifier: Intended Audience :: End Users/Desktop
Classifier: Topic :: Security :: Cryptography
Classifier: Topic :: Utilities
Requires-Python: >=3.7
License-File: LICENSE
Requires-Dist: cryptography
Requires-Dist: click
Requires-Dist: requests
Requires-Dist: pyperclip
Requires-Dist: flask
Requires-Dist: flask-socketio
Requires-Dist: paramiko
Requires-Dist: python-socketio
Dynamic: license-file
